LICENSE.txt
MANIFEST.in
README.rst
setup.py
img/quickstart_0001_728px.png
img/user_guide-_kernels_dict_0001_728px.png
rk/__init__.py
rk/rk.py
rk.egg-info/PKG-INFO
rk.egg-info/SOURCES.txt
rk.egg-info/dependency_links.txt
rk.egg-info/entry_points.txt
rk.egg-info/requires.txt
rk.egg-info/top_level.txt
rk.egg-info/zip-safe
rk/config/argparse.txt
rk/config/kernels.json
rk/config/messages.txt
rk/config/rk.ini
rk/resources/img/logo-32x32.png
rk/resources/img/logo-64x64.png
rk/ssh/__init__.py
rk/ssh/forward.py
rk/ssh/tunnel.py
scripts/rkscript