Metadata-Version: 1.1
Name: rk
Version: 0.3b1
Summary: The remote jupyter kernel/kernels administration utility
Home-page: https://github.com/korniichuk/rk
Author: Ruslan Korniichuk
Author-email: ruslan.korniichuk@gmail.com
License: Public Domain
Download-URL: https://github.com/korniichuk/rk/archive/0.3.zip
Keywords: ipython,jupyter,remote kernel,rk,python2
Platform: Linux
Classifier: Development Status :: 4 - Beta
Classifier: Environment :: Console
Classifier: Intended Audience :: Developers
Classifier: Intended Audience :: Information Technology
Classifier: Intended Audience :: Science/Research
Classifier: Intended Audience :: System Administrators
Classifier: License :: Public Domain
Classifier: Operating System :: POSIX :: Linux
Classifier: Programming Language :: Python
Classifier: Programming Language :: Python :: 2
Classifier: Programming Language :: Python :: 2.7
Classifier: Programming Language :: Python :: 2 :: Only
Classifier: Topic :: Scientific/Engineering
Classifier: Topic :: System :: Systems Administration
Classifier: Topic :: Utilities
